{
  "date": "2026-05-13",
  "limit": 15,
  "generatedAt": "2026-05-13T09:48:20.906862+00:00",
  "clippings": [
    {
      "slug": "aic-591-vessel",
      "label": "Vessel",
      "meta": "Vessel",
      "src": "assets/cutout-clippings/aic-591-vessel.png",
      "sourceUrl": "https://www.artic.edu/artworks/591"
    },
    {
      "slug": "aic-182-kantharos-wine-cup",
      "label": "Kantharos (Wine Cup)",
      "meta": "Vessel",
      "src": "assets/cutout-clippings/aic-182-kantharos-wine-cup.png",
      "sourceUrl": "https://www.artic.edu/artworks/182"
    },
    {
      "slug": "aic-277-kantharos-wine-cup",
      "label": "Kantharos (Wine Cup)",
      "meta": "Vessel",
      "src": "assets/cutout-clippings/aic-277-kantharos-wine-cup.png",
      "sourceUrl": "https://www.artic.edu/artworks/277"
    },
    {
      "slug": "aic-185-kylix-drinking-cup",
      "label": "Kylix (Drinking Cup)",
      "meta": "Vessel",
      "src": "assets/cutout-clippings/aic-185-kylix-drinking-cup.png",
      "sourceUrl": "https://www.artic.edu/artworks/185"
    },
    {
      "slug": "aic-158980-royal-flemish-vase",
      "label": "Royal Flemish Vase",
      "meta": "Glass",
      "src": "assets/cutout-clippings/aic-158980-royal-flemish-vase.png",
      "sourceUrl": "https://www.artic.edu/artworks/158980"
    },
    {
      "slug": "aic-87659-chous-toy-pitcher",
      "label": "Chous (Toy Pitcher)",
      "meta": "Vessel",
      "src": "assets/cutout-clippings/aic-87659-chous-toy-pitcher.png",
      "sourceUrl": "https://www.artic.edu/artworks/87659"
    },
    {
      "slug": "aic-120081-landscape-with-dog",
      "label": "Landscape with Dog",
      "meta": "Painting",
      "src": "assets/cutout-clippings/aic-120081-landscape-with-dog.png",
      "sourceUrl": "https://www.artic.edu/artworks/120081"
    },
    {
      "slug": "aic-180206-statue-of-horus",
      "label": "Statue of Horus",
      "meta": "Sculpture",
      "src": "assets/cutout-clippings/aic-180206-statue-of-horus.png",
      "sourceUrl": "https://www.artic.edu/artworks/180206"
    },
    {
      "slug": "aic-7154-dancer-resting-with-a-fan",
      "label": "Dancer Resting with a Fan",
      "meta": "Drawing and Watercolor",
      "src": "assets/cutout-clippings/aic-7154-dancer-resting-with-a-fan.png",
      "sourceUrl": "https://www.artic.edu/artworks/7154"
    },
    {
      "slug": "aic-144345-timepiece",
      "label": "Timepiece",
      "meta": "Furnishings",
      "src": "assets/cutout-clippings/aic-144345-timepiece.png",
      "sourceUrl": "https://www.artic.edu/artworks/144345"
    },
    {
      "slug": "aic-14973-side-chair",
      "label": "Side Chair",
      "meta": "Furniture",
      "src": "assets/cutout-clippings/aic-14973-side-chair.png",
      "sourceUrl": "https://www.artic.edu/artworks/14973"
    },
    {
      "slug": "aic-87657-chous-toy-pitcher",
      "label": "Chous (Toy Pitcher)",
      "meta": "Vessel",
      "src": "assets/cutout-clippings/aic-87657-chous-toy-pitcher.png",
      "sourceUrl": "https://www.artic.edu/artworks/87657"
    },
    {
      "slug": "aic-156887-table-clock",
      "label": "Table Clock",
      "meta": "Metalwork",
      "src": "assets/cutout-clippings/aic-156887-table-clock.png",
      "sourceUrl": "https://www.artic.edu/artworks/156887"
    },
    {
      "slug": "aic-259-skyphos-drinking-cup",
      "label": "Skyphos (Drinking Cup)",
      "meta": "Vessel",
      "src": "assets/cutout-clippings/aic-259-skyphos-drinking-cup.png",
      "sourceUrl": "https://www.artic.edu/artworks/259"
    },
    {
      "slug": "aic-618-the-arts-ewer-and-basin",
      "label": "\"The Arts\" Ewer and Basin",
      "meta": "Metalwork",
      "src": "assets/cutout-clippings/aic-618-the-arts-ewer-and-basin.png",
      "sourceUrl": "https://www.artic.edu/artworks/618"
    }
  ]
}
